pescatore_cli/__init__.py
pescatore_cli/apps.py
pescatore_cli/functions.py
pescatore_cli/serializers.py
pescatore_cli/settings.py
pescatore_cli/skeleton.py
pescatore_cli/tasks.py
pescatore_cli/utils.py
pescatore_cli/api/__init__.py
pescatore_cli/api/commons.py
pescatore_cli/api/esche.py
pescatore_cli/api/licenze.py
pescatore_cli/api/pescatori.py
pescatore_cli/api/uscite.py
pescatore_cli/cli/__init__.py
pescatore_cli/cli/commands.py
pescatore_cli/cli/commons.py
pescatore_cli/cli/esche.py
pescatore_cli/cli/licenze.py
pescatore_cli/cli/main.py
pescatore_cli/cli/pescatori.py
pescatore_cli/cli/uscite.py
pescatore_cli-0.0.7.dist-info/AUTHORS.rst
pescatore_cli-0.0.7.dist-info/LICENSE.txt
pescatore_cli-0.0.7.dist-info/METADATA
pescatore_cli-0.0.7.dist-info/WHEEL
pescatore_cli-0.0.7.dist-info/entry_points.txt
pescatore_cli-0.0.7.dist-info/top_level.txt
pescatore_cli-0.0.7.dist-info/RECORD
