Metadata-Version: 2.1
Name: pescatore-cli
Version: 0.0.7
Summary: Pescatore client
Home-page: https://bitbucket.org/pai/pescatore-cli
Author: pai
Author-email: paiuolo@gmail.com
License: mit
Platform: any
Classifier: Development Status :: 4 - Beta
Classifier: Programming Language :: Python
Requires-Dist: Django (<2)
Requires-Dist: celery (==4.2.1)
Requires-Dist: cliff (==2.14.0)
Requires-Dist: requests (==2.21.0)
Requires-Dist: djangorestframework (==3.9.1)
Requires-Dist: jsonschema (==2.6.0)
Requires-Dist: python-dateutil (==2.8.0)
Requires-Dist: pandas (==0.24.1)
Provides-Extra: testing
Requires-Dist: pytest ; extra == 'testing'
Requires-Dist: pytest-cov ; extra == 'testing'
